girder_sem_viewer/__init__.py
girder_sem_viewer/rest/__init__.py
girder_sem_viewer/rest/amdee.py
girder_sem_viewer/web_client/dist/girder-plugin-sem-viewer.umd.cjs
girder_sem_viewer/web_client/dist/style.css
girder_sem_viewer-2.3.1.dist-info/licenses/LICENSE
girder_sem_viewer-2.3.1.dist-info/METADATA
girder_sem_viewer-2.3.1.dist-info/WHEEL
girder_sem_viewer-2.3.1.dist-info/entry_points.txt
girder_sem_viewer-2.3.1.dist-info/top_level.txt
girder_sem_viewer-2.3.1.dist-info/RECORD
